{"strssinag":{"string":{"read:own":["*"]}},"sinag":{"string":{"read:own":["*"]}},"sindag":{},"sindafg":{},"sindfafg":{"string":{"read:own":["*"]}},"sindsfafg":{"strinsg":{"read:own":["*"]},"string":{"read:own":["*"]}},"sindssfafg":{"string":{"read:own":["*"]},"strinsg":{"read:own":["*"]}},"sinfdssfafg":{"strinsg":{"read:own":["*"]},"string":{"read:own":["*"]}},"string":{},"sfdtring":{"string":{"read:own":["string"]}},"sfdtridng":{"string":{"read:own":["string"]}},"strdsing":{"string":{"read:own":["string"]}},"strdsfing":{"string":{"read:own":["string"]}},"strdsfidng":{"string":{"read:own":["string"]}},"strdsfiddng":{"string":{"read:own":["string"]}},"strdsfidddng":{"string":{"read:own":["string"]}},"strdsfiddddng":{"string":{"read:own":["string"]}},"strdddg":{"string":{"read:own":["string"]}},"strdddfg":{"string":{"read:own":["string"]}},"strddduyyufg":{"string":{"read:own":["string"]}},"syeenyyufg":{"book":{"read:own":["string"]}},"syeenyyudfg":{"book":{"read:own":["string"]}},"syeeoudfg":{"book":{"read:own":["string"]}},"mauk":{"book":{"read:own":["string"]}},"lida":{"book":{"read:own":["string"]}},"marie":{"book":{"read:own":["string"]}},"strmaniing":{}}